cpe_search/__init__.py
cpe_search/config.json
cpe_search/config_mariadb.json
cpe_search/cpe_search.py
cpe_search/create_sql_statements.json
cpe_search/database_wrapper_functions.py
cpe_search-0.1.9.dist-info/METADATA
cpe_search-0.1.9.dist-info/WHEEL
cpe_search-0.1.9.dist-info/entry_points.txt
cpe_search-0.1.9.dist-info/licenses/LICENSE
cpe_search-0.1.9.dist-info/RECORD
