Metadata-Version: 2.4
Name: cpe_search
Version: 0.1.9
Summary: Search for Common Platform Enumeration (CPE) strings using software names and titles.
Project-URL: Homepage, https://github.com/ra1nb0rn/cpe_search
Project-URL: Documentation, https://github.com/ra1nb0rn/cpe_search
Project-URL: Repository, https://github.com/ra1nb0rn/cpe_search
Project-URL: Issues, https://github.com/ra1nb0rn/cpe_search/issues
Author-email: Dustin Born <search.vulns1@gmail.com>
License-Expression: MIT
License-File: LICENSE
Keywords: cpe,enumeration,match,nvd,platform,search,software
Classifier: Development Status :: 4 - Beta
Classifier: Intended Audience :: Developers
Classifier: Intended Audience :: Information Technology
Classifier: Intended Audience :: System Administrators
Classifier: License :: OSI Approved :: MIT License
Classifier: Programming Language :: Python :: 3
Classifier: Programming Language :: Python :: 3.10
Classifier: Topic :: Security
Classifier: Topic :: System :: Systems Administration
Requires-Python: >=3.10
Requires-Dist: aiohttp
Requires-Dist: aiolimiter
Requires-Dist: requests
Requires-Dist: tqdm
Requires-Dist: ujson
Provides-Extra: all
Requires-Dist: aiohttp; extra == 'all'
Requires-Dist: aiolimiter; extra == 'all'
Requires-Dist: mariadb==1.1.12; extra == 'all'
Requires-Dist: requests; extra == 'all'
Requires-Dist: ujson; extra == 'all'
Provides-Extra: dev
Requires-Dist: black; extra == 'dev'
Requires-Dist: isort; extra == 'dev'
Requires-Dist: pylint; extra == 'dev'
Requires-Dist: ruff; extra == 'dev'
Provides-Extra: mariadb
Requires-Dist: mariadb==1.1.12; extra == 'mariadb'
